xrfm/__about__.py
xrfm/__init__.py
xrfm/tree_utils.py
xrfm/xrfm.py
xrfm/rfm_src/__init__.py
xrfm/rfm_src/class_conversion.py
xrfm/rfm_src/eigenpro.py
xrfm/rfm_src/gpu_utils.py
xrfm/rfm_src/kernel_log_reg.py
xrfm/rfm_src/kernels.py
xrfm/rfm_src/metrics.py
xrfm/rfm_src/recursive_feature_machine.py
xrfm/rfm_src/svd.py
xrfm/rfm_src/utils.py
xrfm-0.4.3.dist-info/METADATA
xrfm-0.4.3.dist-info/WHEEL
xrfm-0.4.3.dist-info/licenses/LICENSE
xrfm-0.4.3.dist-info/RECORD
