Metadata-Version: 2.4
Name: xrfm
Version: 0.4.3
Summary: xRFM: Scalable and interpretable kernel methods for tabular data
Project-URL: Documentation, https://github.com/dmbeaglehole/xrfm#readme
Project-URL: Issues, https://github.com/dmbeaglehole/xrfm/issues
Project-URL: Source, https://github.com/dmbeaglehole/xrfm
Author: Daniel Beaglehole, David Holzmüller
License-Expression: MIT
License-File: LICENSE
Keywords: feature machine,machine learning,recursive,scikit-learn,tabular data,tree-based
Classifier: Development Status :: 4 - Beta
Classifier: License :: OSI Approved :: MIT License
Classifier: Programming Language :: Python
Classifier: Programming Language :: Python :: 3.9
Classifier: Programming Language :: Python :: 3.10
Classifier: Programming Language :: Python :: 3.11
Classifier: Programming Language :: Python :: 3.12
Classifier: Programming Language :: Python :: 3.13
Requires-Python: >=3.9
Requires-Dist: numpy>=1.19.0
Requires-Dist: scikit-learn>=1.4.0
Requires-Dist: torch>=1.8.0
Requires-Dist: tqdm>=4.60.0
Provides-Extra: cu11
Requires-Dist: kermac[cu11]; extra == 'cu11'
Provides-Extra: cu12
Requires-Dist: kermac[cu12]; extra == 'cu12'
